{
    "name": "Versuch 1",
    "date": "2024-04-24",
    "supervisor": {
        "first_name": "Thomas",
        "last_name": "Perger",
        "age": 21
    },
    "subject": {
        "first_name": "Eric",
        "last_name": "Janke",
        "sex": "male",
        "age": 19,
        "max_hr": 205,
        "birth_date": "2005-03-22"
    }
}
{
    "name": "Versuch 2",
    "date": "2024-04-24",
    "supervisor": {
        "first_name": "Eric",
        "last_name": "Janke",
        "age": 19
    },
    "subject": {
        "first_name": "Thomas",
        "last_name": "Perger",
        "sex": "male",
        "age": 21,
        "max_hr": 204,
        "birth_date": "1955-11-11"
    }
}
{
    "name": "Test",
    "date": "2024-04-29",
    "supervisor": {
        "first_name": "Wer auch immer",
        "last_name": "der auch immer",
        "age": 55
    },
    "subject": {
        "first_name": "Eric",
        "last_name": "Janke",
        "sex": "male",
        "age": 19,
        "max_hr": 205,
        "birth_date": "2005-03-22"
    }
}
